logrepl/__init__.py
logrepl/handler.py
logrepl/run.py
logrepl-0.2.7.dist-info/LICENSE
logrepl-0.2.7.dist-info/METADATA
logrepl-0.2.7.dist-info/WHEEL
logrepl-0.2.7.dist-info/entry_points.txt
logrepl-0.2.7.dist-info/RECORD
