Metadata-Version: 2.1
Name: logrepl
Version: 0.2.7
Summary: By this command line tool, you can run a python repl which logs everying into a file.
Home-page: https://github.com/baliuzeger/logrepl
Keywords: repl,log,logging
Author: bali
Author-email: baliuzeger@gmail.com
Requires-Python: >=3.6,<4.0
Classifier: Programming Language :: Python :: 3
Classifier: Programming Language :: Python :: 3.6
Classifier: Programming Language :: Python :: 3.7
Classifier: Programming Language :: Python :: 3.8
Classifier: Programming Language :: Python :: 3.9
Classifier: Programming Language :: Python :: 3.10
Classifier: Programming Language :: Python :: 3.11
Classifier: Programming Language :: Python :: 3.12
Requires-Dist: python-dotenv
Project-URL: Repository, https://github.com/baliuzeger/logrepl
